CHANGES.rst
MANIFEST.in
README.rst
TODO.rst
setup.cfg
setup.py
geometryIO/__init__.py
geometryIO/tests.py
geometryIO.egg-info/PKG-INFO
geometryIO.egg-info/SOURCES.txt
geometryIO.egg-info/dependency_links.txt
geometryIO.egg-info/requires.txt
geometryIO.egg-info/top_level.txt
geometryIO.egg-info/zip-safe