Metadata-Version: 1.1
Name: geometryIO
Version: 0.9.7
Summary: GDAL wrapper for reading and writing geospatial data to a variety of vector formats
Home-page: https://github.com/invisibleroads/geometryIO
Author: Roy Hyunjin Han
Author-email: rhh@crosscompute.com
License: MIT
Keywords: gdal shapely shapefile
Platform: UNKNOWN
Classifier: Intended Audience :: Developers
Classifier: Programming Language :: Python
Classifier: License :: OSI Approved :: MIT License
